wagtail_textract/__init__.py
wagtail_textract/apps.py
wagtail_textract/handlers.py
wagtail_textract/models.py
wagtail_textract/settings.py
wagtail_textract/management/commands/__init__.py
wagtail_textract/management/commands/transcribe_documents.py
wagtail_textract/migrations/0001_initial.py
wagtail_textract/migrations/0001_squashed_0004_auto_20180508_0942.py
wagtail_textract/migrations/0002_auto_20180502_1303.py
wagtail_textract/migrations/0002_auto_20180509_1259.py
wagtail_textract/migrations/0003_auto_20180503_1117.py
wagtail_textract/migrations/0004_auto_20180508_0942.py
wagtail_textract/migrations/__init__.py
wagtail_textract/tests/__init__.py
wagtail_textract/tests/settings.py
wagtail_textract/tests/test_document_class.py
wagtail_textract/tests/test_management_command.py
wagtail_textract/tests/testfiles/test_document.pdf
wagtail_textract-1.2.dev0.dist-info/LICENSE
wagtail_textract-1.2.dev0.dist-info/METADATA
wagtail_textract-1.2.dev0.dist-info/WHEEL
wagtail_textract-1.2.dev0.dist-info/top_level.txt
wagtail_textract-1.2.dev0.dist-info/RECORD
