Metadata-Version: 2.1
Name: wagtail-textract
Version: 1.2.dev0
Summary: Allow searching for text in Documents in the Wagtail content management system
Home-page: https://github.com/fourdigits/wagtail_textract
Author: Kees Hink
Author-email: kees@fourdigits.nl
License: BSD
Platform: UNKNOWN
Classifier: Development Status :: 4 - Beta
Classifier: Environment :: Web Environment
Classifier: Intended Audience :: Developers
Classifier: License :: OSI Approved :: BSD License
Classifier: Operating System :: OS Independent
Classifier: Programming Language :: Python
Classifier: Programming Language :: Python :: 3
Classifier: Programming Language :: Python :: 3.4
Classifier: Programming Language :: Python :: 3.5
Classifier: Programming Language :: Python :: 3.6
Classifier: Programming Language :: Python :: 3.7
Classifier: Framework :: Django
Classifier: Framework :: Django :: 2.0
Classifier: Framework :: Django :: 2.1
Classifier: Framework :: Django :: 2.2
Classifier: Framework :: Wagtail
Classifier: Framework :: Wagtail :: 2
Classifier: Topic :: Internet :: WWW/HTTP :: Site Management
Requires-Dist: wagtail (<2.6,>=2)
Requires-Dist: textract
Provides-Extra: test
Requires-Dist: pytest ; extra == 'test'
Requires-Dist: pytest-django ; extra == 'test'
Requires-Dist: coverage ; extra == 'test'
Requires-Dist: codecov ; extra == 'test'
